execute_for_smarthome.py
execute_for_whabonett.py
execute_webscraping.py
main.py
chatbot/__init__.py
chatbot/chatbot_smarthome/__init__.py
chatbot/chatbot_smarthome/api_smarthome.py
chatbot/chatbot_smarthome/etl_smarthome.py
chatbot/chatbot_whatbonett/etl_whabonett.py
chatbot/database/__init__.py
chatbot/database/config_db.py
chatbot/database/connections.py
chatbot/database/create_schema.py
chatbot/database/models/__init__.py
chatbot/database/models/models_alquiventas.py
chatbot/database/models/models_castillo.py
chatbot/database/models/models_livin.py
chatbot/database/models/models_villacruz.py
chatbot/database/models/tools_models.py
chatbot/database/repositories/__init__.py
chatbot/database/repositories/crud_base.py
chatbot/database/repositories/repository_alquiventas.py
chatbot/database/repositories/repository_castillo.py
chatbot/database/repositories/repository_livin.py
chatbot/database/repositories/repository_villacruz.py
chatbot/processing/__init__.py
chatbot/processing/resumen_chatbot.py
chatbot/processing/tools.py
chatbot/webscraper/__init__.py
chatbot/webscraper/config_driver.py
chatbot/webscraper/customer_chrome_driver.py
chatbot/webscraper/webscraping_chatbot.py
lagencia_chatbot-0.1.2.dist-info/METADATA
lagencia_chatbot-0.1.2.dist-info/WHEEL
lagencia_chatbot-0.1.2.dist-info/top_level.txt
lagencia_chatbot-0.1.2.dist-info/RECORD
