Metadata-Version: 2.4
Name: LAgencia-chatbot
Version: 0.1.2
Summary: Add your description here
Requires-Python: >=3.11
Requires-Dist: colorama>=0.4.6
Requires-Dist: openpyxl>=3.1.5
Requires-Dist: pandas==2.2
Requires-Dist: pymssql>=2.3.11
Requires-Dist: python-dotenv>=1.2.1
Requires-Dist: requests>=2.32.5
Requires-Dist: selenium>=4.39.0
Requires-Dist: sqlalchemy==1.4.53
Requires-Dist: workalendar>=17.0.0
